loggerado-0.2.0.dist-info/METADATA
loggerado-0.2.0.dist-info/WHEEL
loggerado/__init__.py
loggerado/core.py
loggerado-0.2.0.dist-info/RECORD
